fairbench/__init__.py
fairbench/bench/__init__.py
fairbench/bench/loader.py
fairbench/bench/graph/__init__.py
fairbench/bench/graph/algorithms.py
fairbench/bench/graph/experiments.py
fairbench/bench/tabular/__init__.py
fairbench/bench/tabular/adult.py
fairbench/bench/tabular/bank.py
fairbench/bench/tabular/compas.py
fairbench/bench/text/__init__.py
fairbench/bench/text/datasets.py
fairbench/bench/text/models.py
fairbench/bench/vision/__init__.py
fairbench/bench/vision/celeba.py
fairbench/bench/vision/utkface.py
fairbench/bench/vision/waterbirds.py
fairbench/bench/vision/architectures/__init__.py
fairbench/bench/vision/architectures/loader.py
fairbench/bench/vision/architectures/resnet.py
fairbench/bench/vision/architectures/runner.py
fairbench/bench/vision/datasets/__init__.py
fairbench/bench/vision/datasets/celeba.py
fairbench/bench/vision/datasets/downloaders.py
fairbench/bench/vision/datasets/utk_face.py
fairbench/bench/vision/datasets/waterbirds.py
fairbench/bench/vision/datasets/mnist/__init__.py
fairbench/bench/vision/datasets/mnist/biased.py
fairbench/bench/vision/datasets/mnist/color.py
fairbench/bench/vision/datasets/mnist/single.py
fairbench/fallbacks/__init__.py
fairbench/fallbacks/rbo.py
fairbench/fallbacks/read_csv.py
fairbench/fallbacks/learning/__init__.py
fairbench/fallbacks/learning/auc.py
fairbench/fallbacks/learning/logistic_regression.py
fairbench/fallbacks/learning/min_max_scaler.py
fairbench/fallbacks/learning/train_test_split.py
fairbench/v1/__init__.py
fairbench/v1/verification.py
fairbench/v1/blocks/__init__.py
fairbench/v1/blocks/framework.py
fairbench/v1/blocks/expanders/__init__.py
fairbench/v1/blocks/expanders/expanders.py
fairbench/v1/blocks/metrics/__init__.py
fairbench/v1/blocks/metrics/classification.py
fairbench/v1/blocks/metrics/disparate_impact.py
fairbench/v1/blocks/metrics/disparate_mistreatment.py
fairbench/v1/blocks/metrics/ranking.py
fairbench/v1/blocks/metrics/regression.py
fairbench/v1/blocks/reducers/__init__.py
fairbench-0.9.0.dist-info/licenses/LICENSE.txt
fairbench-0.9.0.dist-info/METADATA
fairbench-0.9.0.dist-info/WHEEL
fairbench-0.9.0.dist-info/top_level.txt
fairbench-0.9.0.dist-info/RECORD
