Metadata-Version: 2.4
Name: fairbench
Version: 0.9.0
Summary: A fairness assessment framework
Home-page: https://fairbench.readthedocs.io
Author: Emmanouil (Manios) Krasanakis
Author-email: maniospas@hotmail.com
Classifier: Programming Language :: Python :: 3
Classifier: License :: OSI Approved :: Apache Software License
Classifier: Operating System :: OS Independent
Requires-Python: >=3.9
License-File: LICENSE.txt
Requires-Dist: numpy
Requires-Dist: eagerpy
Requires-Dist: makefun
Requires-Dist: objwrap
Requires-Dist: pyyaml
Requires-Dist: requests
Requires-Dist: ansiplot
Provides-Extra: interactive
Requires-Dist: numpy; extra == "interactive"
Requires-Dist: eagerpy; extra == "interactive"
Requires-Dist: makefun; extra == "interactive"
Requires-Dist: matplotlib; extra == "interactive"
Requires-Dist: scikit-learn; extra == "interactive"
Requires-Dist: pandas; extra == "interactive"
Requires-Dist: objwrap; extra == "interactive"
Requires-Dist: bokeh; extra == "interactive"
Requires-Dist: pyyaml; extra == "interactive"
Requires-Dist: requests; extra == "interactive"
Requires-Dist: ansiplot; extra == "interactive"
Requires-Dist: plotly; extra == "interactive"
Requires-Dist: flask; extra == "interactive"
Provides-Extra: vision
Requires-Dist: numpy; extra == "vision"
Requires-Dist: eagerpy; extra == "vision"
Requires-Dist: makefun; extra == "vision"
Requires-Dist: scikit-learn; extra == "vision"
Requires-Dist: objwrap; extra == "vision"
Requires-Dist: pyyaml; extra == "vision"
Requires-Dist: requests; extra == "vision"
Requires-Dist: ansiplot; extra == "vision"
Requires-Dist: gdown; extra == "vision"
Requires-Dist: torch; extra == "vision"
Requires-Dist: torchvision; extra == "vision"
Requires-Dist: tqdm; extra == "vision"
Provides-Extra: graph
Requires-Dist: numpy; extra == "graph"
Requires-Dist: eagerpy; extra == "graph"
Requires-Dist: makefun; extra == "graph"
Requires-Dist: scikit-learn; extra == "graph"
Requires-Dist: objwrap; extra == "graph"
Requires-Dist: pyyaml; extra == "graph"
Requires-Dist: requests; extra == "graph"
Requires-Dist: ansiplot; extra == "graph"
Requires-Dist: pygrank; extra == "graph"
Provides-Extra: llm
Requires-Dist: numpy; extra == "llm"
Requires-Dist: eagerpy; extra == "llm"
Requires-Dist: makefun; extra == "llm"
Requires-Dist: objwrap; extra == "llm"
Requires-Dist: pyyaml; extra == "llm"
Requires-Dist: requests; extra == "llm"
Requires-Dist: ansiplot; extra == "llm"
Requires-Dist: transformers; extra == "llm"
Dynamic: author
Dynamic: author-email
Dynamic: classifier
Dynamic: description
Dynamic: description-content-type
Dynamic: home-page
Dynamic: license-file
Dynamic: provides-extra
Dynamic: requires-dist
Dynamic: requires-python
Dynamic: summary
